gifted/__init__.py
gifted/cli.py
gifted/gifted.py
gifted-0.0.3.dist-info/DESCRIPTION.rst
gifted-0.0.3.dist-info/entry_points.txt
gifted-0.0.3.dist-info/METADATA
gifted-0.0.3.dist-info/metadata.json
gifted-0.0.3.dist-info/pbr.json
gifted-0.0.3.dist-info/RECORD
gifted-0.0.3.dist-info/top_level.txt
gifted-0.0.3.dist-info/WHEEL
tests/__init__.py
tests/test_cli.py
