Metadata-Version: 2.0
Name: gifted
Version: 0.0.3
Summary: Gif creation and manipulation tool
Home-page: https://github.com/levi-rs/gifted
Author: Levi Noecker
Author-email: levi.noecker@gmail.com
License: UNKNOWN
Keywords: gif animated image
Platform: UNKNOWN
Classifier: Development Status :: 3 - Alpha
Classifier: Intended Audience :: Developers
Classifier: Topic :: Multimedia :: Graphics :: Graphics Conversion
Requires-Dist: numpy
Requires-Dist: Pillow
